themes/__init__.py
themes/datasets.py
themes/registrar.py
themes/resources/gapminder2007.csv
themes/resources/market-indexes.csv.gz
themes/themers/__init__.py
themes/themers/altair.py
themes/themers/base.py
themes/themers/matplotlib.py
themes/themes/__init__.py
themes/themes/base.py
themes/themes/capon_theme.py
themes-0.0.5.dist-info/LICENSE
themes-0.0.5.dist-info/METADATA
themes-0.0.5.dist-info/WHEEL
themes-0.0.5.dist-info/top_level.txt
themes-0.0.5.dist-info/RECORD
