Metadata-Version: 2.1
Name: themes
Version: 0.0.5
Summary: themes: style once, plot everywhere
Home-page: https://github.com/gialdetti/themes
Author: Eyal Gal
Author-email: eyalgl@gmail.com
Classifier: Programming Language :: Python :: 3.10
Classifier: License :: OSI Approved :: GNU General Public License v3 (GPLv3)
Requires-Python: >=3.7
License-File: LICENSE
Requires-Dist: numpy
Requires-Dist: pandas
Requires-Dist: pyyaml
Provides-Extra: dev
Requires-Dist: matplotlib ; extra == 'dev'
Requires-Dist: seaborn ; extra == 'dev'
Requires-Dist: notebook ; extra == 'dev'
Requires-Dist: ipywidgets ; extra == 'dev'
Requires-Dist: altair ; extra == 'dev'
Requires-Dist: black >=24.3.0 ; extra == 'dev'
Requires-Dist: pytest ; extra == 'dev'
Requires-Dist: ipython ; extra == 'dev'
Requires-Dist: tox ; extra == 'dev'
Provides-Extra: docs
Requires-Dist: black >=24.3.0 ; extra == 'docs'
Provides-Extra: test
Requires-Dist: pytest ; extra == 'test'
Requires-Dist: ipython ; extra == 'test'
Requires-Dist: tox ; extra == 'test'
